{
    "experiment": "trainWithParameters",
    "inference_type": "ADVI",
    "layers": 2,
    "input_definition_version": 1,
    "split": 0.3,
    "take_every": 3,
    "iter": 70000,
    "n_hidden": 20,
    "seed": 0,
    "gesture_type": "static",
    "model_filename": "network99",
    "full_dataload": false,
    "engine": "PyMC",
    "save": true,
    "test": true,
    "Gs": [
        "grab",
        "pinch",
        "point",
        "two",
        "three",
        "four",
        "five",
        "thumbsup"
    ],
    "learn_path": "/home/petr/crow-base/src/teleop_gesture_toolbox/include/data/learning/",
    "network_path": "/home/petr/crow-base/src/teleop_gesture_toolbox/include/data/trained_networks/",
    "counts": [
        2000,
        2000,
        2000,
        2000,
        2000,
        2000,
        2000,
        2000
    ],
    "acc_train": 99,
    "acc_test": 99
}